warning_parser.py
warning_parser-1.0.0.dist-info/LICENSE
warning_parser-1.0.0.dist-info/METADATA
warning_parser-1.0.0.dist-info/WHEEL
warning_parser-1.0.0.dist-info/top_level.txt
warning_parser-1.0.0.dist-info/RECORD
