Metadata-Version: 2.1
Name: warning-parser
Version: 1.0.0
Summary: Parses compilers' outputs to retrieve warnings
Home-page: https://github.com/qdewaghe/warning-parser
Author: Quentin Dewaghe
Author-email: q.dewaghe@gmail.com
License: UNKNOWN
Platform: UNKNOWN
Classifier: Programming Language :: Python :: 3
Classifier: License :: OSI Approved :: MIT License
Classifier: Operating System :: POSIX :: Linux
Classifier: Natural Language :: English
Requires-Python: >=3.6
Provides-Extra: dev
Requires-Dist: pytest (>=3.7) ; extra == 'dev'
